html_to_delta/__init__.py
html_to_delta/converter.py
tests/__init__.py
tests/test_converter.py
html_to_quill_delta-0.1.0.dist-info/LICENSE
html_to_quill_delta-0.1.0.dist-info/METADATA
html_to_quill_delta-0.1.0.dist-info/WHEEL
html_to_quill_delta-0.1.0.dist-info/top_level.txt
html_to_quill_delta-0.1.0.dist-info/RECORD
